chatto/__init__.py
chatto/__main__.py
chatto/channel.py
chatto/errors.py
chatto/events.py
chatto/message.py
chatto/oauth.py
chatto/secrets.py
chatto/stream.py
chatto/ux.py
chatto/youtube.py
chatto-0.5.0.dist-info/LICENSE
chatto-0.5.0.dist-info/METADATA
chatto-0.5.0.dist-info/WHEEL
chatto-0.5.0.dist-info/top_level.txt
chatto-0.5.0.dist-info/RECORD
