Metadata-Version: 2.1
Name: chatto
Version: 0.5.0
Summary: A unified API wrapper for YouTube and Twitch chat bots.
Home-page: https://github.com/parafoxia/chatto
Author: Ethan Henderson
Author-email: ethan.henderson.1998@gmail.com
License: BSD 3-Clause 'New' or 'Revised' License
Project-URL: Documentation, https://parafoxia.github.io/chatto/chatto/
Project-URL: Source, https://github.com/parafoxia/chatto
Project-URL: Bug Tracker, https://github.com/parafoxia/chatto/issues
Project-URL: CI, https://github.com/parafoxia/chatto/actions
Platform: UNKNOWN
Classifier: Development Status :: 3 - Alpha
Classifier: Intended Audience :: Developers
Classifier: License :: OSI Approved :: BSD License
Classifier: Natural Language :: English
Classifier: Operating System :: MacOS
Classifier: Operating System :: Microsoft :: Windows
Classifier: Operating System :: OS Independent
Classifier: Operating System :: POSIX
Classifier: Operating System :: Unix
Classifier: Programming Language :: Python :: 3
Classifier: Programming Language :: Python :: 3 :: Only
Classifier: Programming Language :: Python :: 3.8
Classifier: Programming Language :: Python :: 3.9
Classifier: Programming Language :: Python :: 3.10
Classifier: Programming Language :: Python :: Implementation :: CPython
Classifier: Programming Language :: Python :: Implementation :: PyPy
Classifier: Topic :: Communications :: Chat
Classifier: Topic :: Internet
Classifier: Topic :: Software Development
Classifier: Typing :: Typed
Requires-Python: >=3.8.0,<3.11
License-File: LICENSE
Requires-Dist: aiofiles (~=0.8.0)
Requires-Dist: aiohttp (<4,>=3.8.1)
Requires-Dist: python-dateutil (<3,>=2.8.2)
Provides-Extra: types
Requires-Dist: types-aiofiles (==0.7.3) ; extra == 'types'
Requires-Dist: types-python-dateutil (==2.8.4) ; extra == 'types'
